parserutils/__init__.py
parserutils/collections.py
parserutils/dates.py
parserutils/elements.py
parserutils/numbers.py
parserutils/strings.py
parserutils/tests/__init__.py
parserutils/tests/collection_tests.py
parserutils/tests/data/elem_data_ascii.xml
parserutils/tests/data/elem_data_unicode.xml
parserutils/tests/data/namespace_data.xml
parserutils/tests/date_tests.py
parserutils/tests/element_tests.py
parserutils/tests/number_tests.py
parserutils/tests/string_tests.py
parserutils/tests/url_tests.py
parserutils/urls.py
parserutils-2.0.1.dist-info/LICENSE
parserutils-2.0.1.dist-info/WHEEL
parserutils-2.0.1.dist-info/METADATA
parserutils-2.0.1.dist-info/RECORD
