Metadata-Version: 2.1
Name: parserutils
Version: 2.0.1
Summary: A collection of performant parsing utilities
Home-page: https://github.com/consbio/parserutils/
License: BSD
Keywords: parser,parsing,utils,utilities,collections,dates,elements,numbers,strings,url,xml
Author: dharvey-consbio
Author-email: dani.harvey@consbio.org
Requires-Python: >=3.6,<4.0
Classifier: License :: Other/Proprietary License
Classifier: Programming Language :: Python :: 3
Classifier: Programming Language :: Python :: 3.10
Classifier: Programming Language :: Python :: 3.6
Classifier: Programming Language :: Python :: 3.7
Classifier: Programming Language :: Python :: 3.8
Classifier: Programming Language :: Python :: 3.9
Requires-Dist: defusedxml (>=0.7.1,<0.8.0)
Requires-Dist: python-dateutil (>=2.8.2,<3.0.0)
Project-URL: Repository, https://github.com/consbio/parserutils/
